{
  "project_info": {
    "project_number": "542974649643",
    "project_id": "aeoroport-c9a4d",
    "storage_bucket": "aeoroport-c9a4d.appspot.com"
  },
  "client": [
    {
      "client_info": {
        "mobilesdk_app_id": "1:542974649643:android:a6959de58299923f3cd16e",
        "android_client_info": {
          "package_name": "com.example.avion"
        }
      },
      "oauth_client": [],
      "api_key": [
        {
          "current_key": "AIzaSyDbJ2kOjQhCqXzKvEHoSEQb7qLo3IWhT0I"
        }
      ],
      "services": {
        "appinvite_service": {
          "other_platform_oauth_client": []
        }
      }
    }
  ],
  "configuration_version": "1"
}